README.md
setup.cfg
setup.py
jlp/__init__.py
jlp/__main__.py
jlp/jlp.py
jlp.egg-info/PKG-INFO
jlp.egg-info/SOURCES.txt
jlp.egg-info/dependency_links.txt
jlp.egg-info/entry_points.txt
jlp.egg-info/requires.txt
jlp.egg-info/top_level.txt