Metadata-Version: 1.0
Name: jlp
Version: 0.1a0
Summary: tool for installing Julia packages
Home-page: https://github.com/sktnkysh/jlp_Julia-Package-Manager
Author: FUKUDA Yutaro
Author-email: sktnkysh+dev@gmai.com
License: MIT
Platform: UNKNOWN
